source_freshcaller/__init__.py
source_freshcaller/manifest.yaml
source_freshcaller/run.py
source_freshcaller/source.py
airbyte_source_freshcaller-0.5.4.dist-info/METADATA
airbyte_source_freshcaller-0.5.4.dist-info/WHEEL
airbyte_source_freshcaller-0.5.4.dist-info/entry_points.txt
airbyte_source_freshcaller-0.5.4.dist-info/RECORD
