Metadata-Version: 2.1
Name: airbyte-source-freshcaller
Version: 0.5.4
Summary: Source implementation for Freshcaller
Home-page: https://airbyte.com
License: ELv2
Author: Airbyte
Author-email: contact@airbyte.io
Requires-Python: >=3.10,<3.13
Classifier: License :: Other/Proprietary License
Classifier: Programming Language :: Python :: 3
Classifier: Programming Language :: Python :: 3.10
Classifier: Programming Language :: Python :: 3.11
Classifier: Programming Language :: Python :: 3.12
Requires-Dist: airbyte-cdk (>=7.0.4,<8.0.0)
Project-URL: Documentation, https://docs.airbyte.com/integrations/sources/freshcaller
Project-URL: Repository, https://github.com/airbytehq/airbyte
